README.md
setup.py
envvarconf/__init__.py
envvarconf/exceptions.py
envvarconf/inspection.py
envvarconf/printing.py
envvarconf/validation.py
envvarconf.egg-info/PKG-INFO
envvarconf.egg-info/SOURCES.txt
envvarconf.egg-info/dependency_links.txt
envvarconf.egg-info/requires.txt
envvarconf.egg-info/top_level.txt
envvarconf/converters/__init__.py
envvarconf/converters/base.py
envvarconf/converters/string_converter.py
envvarconf/loaders/__init__.py
envvarconf/loaders/base.py
envvarconf/loaders/environ.py
envvarconf/mixins/__init__.py
envvarconf/mixins/logger.py
envvarconf/mixins/sentry.py
tests/__init__.py
tests/test_converters.py
tests/test_settings.py