Metadata-Version: 2.1
Name: envvarconf
Version: 1.4
Summary: Safe app configuration from environment variables without extra dependencies
Home-page: https://github.com/a1fred/envvarconf
Author: a1fred
Author-email: demalf@gmail.com
License: MIT
Platform: UNKNOWN
Classifier: Environment :: Console
Classifier: Operating System :: POSIX :: Linux
Classifier: Operating System :: MacOS :: MacOS X
Classifier: Development Status :: 4 - Beta
Classifier: Programming Language :: Python :: 3.5
Classifier: Programming Language :: Python :: 3.6
Classifier: Programming Language :: Python :: 3.7
Classifier: Programming Language :: Python :: 3.8
Classifier: Programming Language :: Python :: 3.9
Provides-Extra: sentry
Provides-Extra: all
